is_bot/__init__.py
is_bot/_is_bot.py
is_bot/_patterns.py
is_bot-0.3.4.dist-info/licenses/LICENSE.txt
is_bot-0.3.4.dist-info/METADATA
is_bot-0.3.4.dist-info/WHEEL
is_bot-0.3.4.dist-info/top_level.txt
is_bot-0.3.4.dist-info/RECORD
