Metadata-Version: 2.4
Name: is-bot
Version: 0.3.4
Summary: Python package to detect bots/crawlers/spiders via user-agent
Author-email: Roman Snegirev <snegiryev@gmail.com>
License:                                  Apache License
Project-URL: homepage, https://github.com/romis2012/is-bot
Project-URL: repository, https://github.com/romis2012/is-bot
Keywords: python,bots,crawlers,web-crawlers,user-agent,user-agent-parser
Classifier: Development Status :: 4 - Beta
Classifier: Programming Language :: Python
Classifier: Programming Language :: Python :: 3
Classifier: Programming Language :: Python :: 3 :: Only
Classifier: Programming Language :: Python :: 3.8
Classifier: Programming Language :: Python :: 3.9
Classifier: Programming Language :: Python :: 3.10
Classifier: Programming Language :: Python :: 3.11
Classifier: Programming Language :: Python :: 3.12
Classifier: Programming Language :: Python :: 3.13
Classifier: Operating System :: MacOS
Classifier: Operating System :: Microsoft
Classifier: Operating System :: POSIX :: Linux
Classifier: Topic :: Internet :: WWW/HTTP
Classifier: Intended Audience :: Developers
Requires-Python: >=3.8.0
License-File: LICENSE.txt
Requires-Dist: regex>=2022.8.17
Dynamic: license-file
